{
  "id": "arabic-5eme",
  "nameFr": "اللغة العربية",
  "description": "نقرأ نصوصًا طويلةً ونفهمها، ونبني الجملة الكبرى والصغرى ونميّز المسند والمسند إليه، ونتعرّف الفعل اللازم والمتعدّي والمفعول به، والمبنيّ للمعلوم والمبنيّ للمجهول، والمفاعيل (فيه والمطلق ولأجله) والحال، وكان وأخواتها وإنّ وأخواتها، ونصرّف الفعل المجرّد والمزيد على الميزان الصرفيّ، ونتقن همزة الوصل والقطع والهمزة المتوسّطة والمتطرّفة، وفق برنامج اللغة العربية للسنة الخامسة من التعليم الأساسي",
  "attribute": "Esprit",
  "colorToken": "subject-arabic",
  "icon": "Languages",
  "displayOrder": 3,
  "contentLanguage": "ar",
  "themeId": "ecole-tn",
  "gradeSlug": "5eme-base"
}
